usd_inr_converter/__init__.py
usd_inr_converter/converter.py
usd_inr_converter-0.1.dist-info/METADATA
usd_inr_converter-0.1.dist-info/WHEEL
usd_inr_converter-0.1.dist-info/top_level.txt
usd_inr_converter-0.1.dist-info/RECORD
