Metadata-Version: 2.1
Name: usd-inr-converter
Version: 0.1
Summary: A Simple currency converter package
Home-page: https://github.com/aaerrolla/usd_inr_converter
Author-email: aaerrolla@gmail.com
Requires-Dist: requests
